{
  "id": "notion-workspace",
  "slug": "notion-workspace",
  "name": "文档和知识库太乱?",
  "description": "Notion 文档管理工作台",
  "tags": [
    "Notion",
    "文档管理",
    "知识库"
  ],
  "profession": [
    "management",
    "operations",
    "technical"
  ],
  "industry": [
    "software",
    "education",
    "media"
  ],
  "hidden": false,
  "auth": {
    "type": "api-key",
    "header": "X-API-Key",
    "tenantHeader": "X-Tenant-Id"
  },
  "comingSoon": false,
  "externalLink": "https://www.notion.com/",
  "invocationMode": "external-link",
  "invocation": {
    "type": "external-link",
    "externalLink": "https://www.notion.com/"
  }
}
